unfazed_taskiq/__init__.py
unfazed_taskiq/decorators.py
unfazed_taskiq/lifespan.py
unfazed_taskiq/logger.py
unfazed_taskiq/middleware.py
unfazed_taskiq/settings.py
unfazed_taskiq/agent/__init__.py
unfazed_taskiq/agent/handler.py
unfazed_taskiq/agent/model.py
unfazed_taskiq/cli/__init__.py
unfazed_taskiq/cli/scheduler/__init__.py
unfazed_taskiq/cli/scheduler/args.py
unfazed_taskiq/cli/scheduler/cmd.py
unfazed_taskiq/cli/worker/__init__.py
unfazed_taskiq/cli/worker/cmd.py
unfazed_taskiq/contrib/scheduler/__init__.py
unfazed_taskiq/contrib/scheduler/admin.py
unfazed_taskiq/contrib/scheduler/app.py
unfazed_taskiq/contrib/scheduler/models.py
unfazed_taskiq/contrib/scheduler/serializer.py
unfazed_taskiq/contrib/scheduler/settings.py
unfazed_taskiq/contrib/scheduler/sources.py
unfazed_taskiq/registry/__init__.py
unfazed_taskiq/registry/task.py
unfazed_taskiq/schema/__init__.py
unfazed_taskiq/schema/registry/__init__.py
unfazed_taskiq/schema/registry/task.py
unfazed_taskiq-0.0.7.dist-info/METADATA
unfazed_taskiq-0.0.7.dist-info/WHEEL
unfazed_taskiq-0.0.7.dist-info/entry_points.txt
unfazed_taskiq-0.0.7.dist-info/RECORD
