Metadata-Version: 2.4
Name: unfazed-taskiq
Version: 0.0.7
Summary: Taskiq Plugin for Unfazed
Requires-Python: >=3.12
Requires-Dist: taskiq-aio-pika>=0.4.2
Requires-Dist: taskiq>=0.11.16
Requires-Dist: unfazed>=0.0.16
